apache_beam_jupyterlab_sidepanel/__init__.py
apache_beam_jupyterlab_sidepanel/_version.py
apache_beam_jupyterlab_sidepanel/labextension/package.json
apache_beam_jupyterlab_sidepanel/labextension/static/1013.f07f46a601cd3f85d515.js
apache_beam_jupyterlab_sidepanel/labextension/static/1170.7dd2893f8e2a8b0394f5.js
apache_beam_jupyterlab_sidepanel/labextension/static/1368.822bb63cd7c38a7016e3.js
apache_beam_jupyterlab_sidepanel/labextension/static/1412.3a9fa8d918aad98e374d.js
apache_beam_jupyterlab_sidepanel/labextension/static/1412.3a9fa8d918aad98e374d.js.LICENSE.txt
apache_beam_jupyterlab_sidepanel/labextension/static/1413.507b5f5e95dc0bcb7677.js
apache_beam_jupyterlab_sidepanel/labextension/static/1413.507b5f5e95dc0bcb7677.js.LICENSE.txt
apache_beam_jupyterlab_sidepanel/labextension/static/161.a746323997844beeb204.js
apache_beam_jupyterlab_sidepanel/labextension/static/167.b3732d84278d33630848.js
apache_beam_jupyterlab_sidepanel/labextension/static/1769.8f40a8b4f057088b53ce.js
apache_beam_jupyterlab_sidepanel/labextension/static/1769.8f40a8b4f057088b53ce.js.LICENSE.txt
apache_beam_jupyterlab_sidepanel/labextension/static/1794.cab46fefb24990c2fd53.js
apache_beam_jupyterlab_sidepanel/labextension/static/1794.cab46fefb24990c2fd53.js.LICENSE.txt
apache_beam_jupyterlab_sidepanel/labextension/static/2044.bae0e50675f5a0c6ee07.js
apache_beam_jupyterlab_sidepanel/labextension/static/2044.bae0e50675f5a0c6ee07.js.LICENSE.txt
apache_beam_jupyterlab_sidepanel/labextension/static/2238.d18329516286776762cd.js
apache_beam_jupyterlab_sidepanel/labextension/static/2526.70f41df09eaa24fdc395.js
apache_beam_jupyterlab_sidepanel/labextension/static/2542.a746323997844beeb204.js
apache_beam_jupyterlab_sidepanel/labextension/static/2552.e207f507a99f159f1b72.js
apache_beam_jupyterlab_sidepanel/labextension/static/2552.e207f507a99f159f1b72.js.LICENSE.txt
apache_beam_jupyterlab_sidepanel/labextension/static/2627.deb94a97d5986c283850.js
apache_beam_jupyterlab_sidepanel-4.0.0.dist-info/METADATA
apache_beam_jupyterlab_sidepanel-4.0.0.dist-info/WHEEL
apache_beam_jupyterlab_sidepanel-4.0.0.dist-info/RECORD
