Metadata-Version: 2.4
Name: apache_beam_jupyterlab_sidepanel
Version: 4.0.0
Summary: JupyterLab Sidepanel for Apache Beam
Author-email: Apache Beam <dev@beam.apache.org>
License: Apache-2.0
Classifier: Framework :: Jupyter
Classifier: Framework :: Jupyter :: JupyterLab
Classifier: Framework :: Jupyter :: JupyterLab :: 4
Classifier: License :: OSI Approved :: Apache Software License
Classifier: Programming Language :: Python :: 3
Requires-Python: >=3.9
Requires-Dist: jupyter-server>=2.0.0
Requires-Dist: jupyterlab<5,>=4.0.0
